[
    {
        "Category": "VAP",
        "er": "KR",
        "Website": "Coupang",
        "URL": "https://www.coupang.com/vp/products/8688699077?itemId=25226013844&vendorItemId=92222251019&q=lost+mary&itemsCount=32&searchId=2a6595911338898&rank=11&searchRank=11"
    },
    {
        "Category": "VAP",
        "er": "KR",
        "Website": "Coupang",
        "URL": "https://www.coupang.com/vp/products/8688699077?itemId=25226013846&vendorItemId=92222251027&q=lost+mary&itemsCount=32&searchId=2a6595911338898&rank=12&searchRank=12"
    },
    {
        "Category": "VAP",
        "er": "KR",
        "Website": "Coupang",
        "URL": "https://www.coupang.com/vp/products/8688699077?itemId=25226013848&vendorItemId=92222251048&q=lost+mary&itemsCount=32&searchId=2a6595911338898&rank=13&searchRank=13"
    },
    {
        "Category": "VAP",
        "er": "KR",
        "Website": "Coupang",
        "URL": "https://www.coupang.com/vp/products/6095013769?itemId=24017433276&vendorItemId=91038035846&q=lost+mary&itemsCount=32&searchId=2a6595911338898&rank=14&searchRank=14"
    },
    {
        "Category": "VAP",
        "er": "KR",
        "Website": "Coupang",
        "URL": "https://www.coupang.com/vp/products/8594867655?itemId=24201615008&vendorItemId=90877738256&q=lost+mary&itemsCount=32&searchId=2a6595911338898&rank=15&searchRank=15"
    }
]